{
  "animateLoading": true,
  "borderRadius": "{{appsmith.theme.borderRadius.appBorderRadius}}",
  "bottomRow": 13,
  "dynamicBindingPathList": [
    {
      "key": "truncateButtonColor"
    },
    {
      "key": "borderRadius"
    }
  ],
  "dynamicHeight": "AUTO_HEIGHT",
  "dynamicTriggerPathList": [],
  "fontFamily": "System Default",
  "fontSize": "1rem",
  "fontStyle": "BOLD",
  "isLoading": false,
  "isVisible": true,
  "key": "7v6p93oa31",
  "leftColumn": 6,
  "maxDynamicHeight": 9000,
  "minDynamicHeight": 4,
  "minWidth": 450,
  "mobileBottomRow": 10,
  "mobileLeftColumn": 0,
  "mobileRightColumn": 11,
  "mobileTopRow": 6,
  "needsErrorInfo": false,
  "originalBottomRow": 11,
  "originalTopRow": 4,
  "overflow": "NONE",
  "parentColumnSpace": 15.90625,
  "parentId": "22bv6hewzs",
  "parentRowSpace": 10,
  "renderMode": "CANVAS",
  "responsiveBehavior": "fill",
  "rightColumn": 61,
  "shouldScrollContents": true,
  "shouldTruncate": false,
  "text": "搜索框内可搜索要支出的经费（编号或名称）\n\n点击后可为当前经费新增支出",
  "textAlign": "LEFT",
  "textColor": "#581c87",
  "topRow": 6,
  "truncateButtonColor": "{{appsmith.theme.colors.primaryColor}}",
  "type": "TEXT_WIDGET",
  "version": 1,
  "widgetId": "sbrvy378eb",
  "widgetName": "Text6"
}